spdict/__init__.py
spdict/__main__.py
spdict/conjugate.py
spdict/options.py
spdict/translate.py
Spdict-0.1.3.dist-info/METADATA
Spdict-0.1.3.dist-info/WHEEL
Spdict-0.1.3.dist-info/entry_points.txt
Spdict-0.1.3.dist-info/top_level.txt
Spdict-0.1.3.dist-info/RECORD
